carvekit/__init__.py
carvekit/__main__.py
carvekit/api/__init__.py
carvekit/api/high.py
carvekit/api/interface.py
carvekit/ml/__init__.py
carvekit/ml/arch/__init__.py
carvekit/ml/arch/basnet/__init__.py
carvekit/ml/arch/basnet/basnet.py
carvekit/ml/arch/fba_matting/__init__.py
carvekit/ml/arch/fba_matting/layers_WS.py
carvekit/ml/arch/fba_matting/models.py
carvekit/ml/arch/fba_matting/resnet_GN_WS.py
carvekit/ml/arch/fba_matting/resnet_bn.py
carvekit/ml/arch/fba_matting/transforms.py
carvekit/ml/arch/tracerb7/__init__.py
carvekit/ml/arch/tracerb7/att_modules.py
carvekit/ml/arch/tracerb7/conv_modules.py
carvekit/ml/arch/tracerb7/effi_utils.py
carvekit/ml/arch/tracerb7/efficientnet.py
carvekit/ml/arch/tracerb7/tracer.py
carvekit/ml/arch/u2net/__init__.py
carvekit/ml/arch/u2net/u2net.py
carvekit/ml/files/__init__.py
carvekit/ml/files/models_loc.py
carvekit/ml/wrap/__init__.py
carvekit/ml/wrap/basnet.py
carvekit/ml/wrap/deeplab_v3.py
carvekit/ml/wrap/fba_matting.py
carvekit/ml/wrap/tracer_b7.py
carvekit/ml/wrap/u2net.py
carvekit/pipelines/__init__.py
carvekit/pipelines/postprocessing.py
carvekit/pipelines/preprocessing.py
carvekit/trimap/__init__.py
carvekit/trimap/add_ops.py
carvekit/trimap/cv_gen.py
carvekit/trimap/generator.py
carvekit/utils/__init__.py
carvekit/utils/download_models.py
carvekit/utils/fs_utils.py
carvekit/utils/image_utils.py
carvekit/utils/mask_utils.py
carvekit/utils/models_utils.py
carvekit/utils/pool_utils.py
carvekit/web/__init__.py
carvekit/web/app.py
carvekit/web/deps.py
carvekit/web/handlers/__init__.py
carvekit/web/handlers/response.py
carvekit/web/other/__init__.py
carvekit/web/other/removebg.py
carvekit/web/responses/__init__.py
carvekit/web/responses/api.py
carvekit/web/routers/__init__.py
carvekit/web/routers/api_router.py
carvekit/web/schemas/__init__.py
carvekit/web/schemas/config.py
carvekit/web/schemas/request.py
carvekit/web/utils/__init__.py
carvekit/web/utils/init_utils.py
carvekit/web/utils/net_utils.py
carvekit-4.1.2.dist-info/LICENSE
carvekit-4.1.2.dist-info/METADATA
carvekit-4.1.2.dist-info/WHEEL
carvekit-4.1.2.dist-info/entry_points.txt
carvekit-4.1.2.dist-info/top_level.txt
carvekit-4.1.2.dist-info/RECORD
