Metadata-Version: 2.1
Name: carvekit
Version: 4.1.2
Summary: Open-Source background removal framework
Home-page: https://github.com/OPHoperHPO/image-background-remove-tool
Author: Nikita Selin (Anodev)
Author-email: farvard34@gmail.com
License: Apache License v2.0
Keywords: ml,carvekit,background removal,neural networks,machine learning,remove bg
Classifier: Development Status :: 5 - Production/Stable
Classifier: Environment :: Web Environment
Classifier: Intended Audience :: Developers
Classifier: License :: OSI Approved :: Apache Software License
Classifier: Natural Language :: English
Classifier: Operating System :: OS Independent
Classifier: Programming Language :: Python :: 3.10
Classifier: Topic :: Scientific/Engineering :: Artificial Intelligence
Requires-Python: >=3.8
License-File: LICENSE
Requires-Dist: requests >=2.31.0
Requires-Dist: torch >=2.2.2
Requires-Dist: Pillow >=10.3.0
Requires-Dist: typing >=3.7.4.3
Requires-Dist: torchvision >=0.17.2
Requires-Dist: opencv-python >=4.9.0.80
Requires-Dist: numpy >=1.26.4
Requires-Dist: loguru >=0.7.2
Requires-Dist: uvicorn >=0.29.0
Requires-Dist: fastapi >=0.110.1
Requires-Dist: pydantic >=2.6.4
Requires-Dist: click >=8.1.7
Requires-Dist: tqdm >=4.66.2
Requires-Dist: setuptools >=69.2.0
Requires-Dist: aiofiles >=23.2.1
Requires-Dist: python-multipart >=0.0.9
